{
    "profil":[
        {
            "nama": "Cahyo Dwi",
            "kampus": "unwidha",
            "contact": "https://github.com/brodwi",
            "gambar": "https://foto-beta.vercel.app/src/cahyo.jpg"
        },
        {
            "nama": "Agustina",
            "kampus": "ITB AAS",
            "contact": "https://github.com/Anggaranii",
            "gambar": "https://foto-beta.vercel.app/src/agustina.jpg"
        },
        {
            "nama": "wildan ibra",
            "kampus": "amikom",
            "contact": "https://github.com/wildanibr"
        },
        {
            "nama": "Fadhila",
            "kampus": "ITB AAS",
            "contact": "https://github.com/fadhilahgi",
            "gambar": "https://foto-beta.vercel.app/src/fadhila.jpg"
        }
    ]
}